{"nodes": [{"id": "admindecisionrequest", "label": "AdminDecisionRequest.java", "file_type": "code", "source_file": "src\\main\\java\\kz\\hrms\\splitupauth\\dto\\AdminDecisionRequest.java", "source_location": "L1"}, {"id": "admindecisionrequest_admindecisionrequest", "label": "AdminDecisionRequest", "file_type": "code", "source_file": "src\\main\\java\\kz\\hrms\\splitupauth\\dto\\AdminDecisionRequest.java", "source_location": "L7"}], "edges": [{"source": "admindecisionrequest", "target": "notblank", "relation": "imports", "confidence": "EXTRACTED", "source_file": "src\\main\\java\\kz\\hrms\\splitupauth\\dto\\AdminDecisionRequest.java", "source_location": "L3", "weight": 1.0}, {"source": "admindecisionrequest", "target": "size", "relation": "imports", "confidence": "EXTRACTED", "source_file": "src\\main\\java\\kz\\hrms\\splitupauth\\dto\\AdminDecisionRequest.java", "source_location": "L4", "weight": 1.0}, {"source": "admindecisionrequest", "target": "data", "relation": "imports", "confidence": "EXTRACTED", "source_file": "src\\main\\java\\kz\\hrms\\splitupauth\\dto\\AdminDecisionRequest.java", "source_location": "L5", "weight": 1.0}, {"source": "admindecisionrequest", "target": "admindecisionrequest_admindecisionrequest", "relation": "contains", "confidence": "EXTRACTED", "source_file": "src\\main\\java\\kz\\hrms\\splitupauth\\dto\\AdminDecisionRequest.java", "source_location": "L7", "weight": 1.0}]}