{"nodes": [{"id": "adminactionlog", "label": "AdminActionLog.java", "file_type": "code", "source_file": "src\\main\\java\\kz\\hrms\\splitupauth\\entity\\AdminActionLog.java", "source_location": "L1"}, {"id": "adminactionlog_adminactionlog", "label": "AdminActionLog", "file_type": "code", "source_file": "src\\main\\java\\kz\\hrms\\splitupauth\\entity\\AdminActionLog.java", "source_location": "L15"}, {"id": "adminactionlog_adminactionlog_oncreate", "label": ".onCreate()", "file_type": "code", "source_file": "src\\main\\java\\kz\\hrms\\splitupauth\\entity\\AdminActionLog.java", "source_location": "L70"}], "edges": [{"source": "adminactionlog", "target": "jsonnode", "relation": "imports", "confidence": "EXTRACTED", "source_file": "src\\main\\java\\kz\\hrms\\splitupauth\\entity\\AdminActionLog.java", "source_location": "L3", "weight": 1.0}, {"source": "adminactionlog", "target": "persistence", "relation": "imports", "confidence": "EXTRACTED", "source_file": "src\\main\\java\\kz\\hrms\\splitupauth\\entity\\AdminActionLog.java", "source_location": "L4", "weight": 1.0}, {"source": "adminactionlog", "target": "allargsconstructor", "relation": "imports", "confidence": "EXTRACTED", "source_file": "src\\main\\java\\kz\\hrms\\splitupauth\\entity\\AdminActionLog.java", "source_location": "L5", "weight": 1.0}, {"source": "adminactionlog", "target": "builder", "relation": "imports", "confidence": "EXTRACTED", "source_file": "src\\main\\java\\kz\\hrms\\splitupauth\\entity\\AdminActionLog.java", "source_location": "L6", "weight": 1.0}, {"source": "adminactionlog", "target": "data", "relation": "imports", "confidence": "EXTRACTED", "source_file": "src\\main\\java\\kz\\hrms\\splitupauth\\entity\\AdminActionLog.java", "source_location": "L7", "weight": 1.0}, {"source": "adminactionlog", "target": "noargsconstructor", "relation": "imports", "confidence": "EXTRACTED", "source_file": "src\\main\\java\\kz\\hrms\\splitupauth\\entity\\AdminActionLog.java", "source_location": "L8", "weight": 1.0}, {"source": "adminactionlog", "target": "jdbctypecode", "relation": "imports", "confidence": "EXTRACTED", "source_file": "src\\main\\java\\kz\\hrms\\splitupauth\\entity\\AdminActionLog.java", "source_location": "L9", "weight": 1.0}, {"source": "adminactionlog", "target": "sqltypes", "relation": "imports", "confidence": "EXTRACTED", "source_file": "src\\main\\java\\kz\\hrms\\splitupauth\\entity\\AdminActionLog.java", "source_location": "L10", "weight": 1.0}, {"source": "adminactionlog", "target": "localdatetime", "relation": "imports", "confidence": "EXTRACTED", "source_file": "src\\main\\java\\kz\\hrms\\splitupauth\\entity\\AdminActionLog.java", "source_location": "L12", "weight": 1.0}, {"source": "adminactionlog", "target": "uuid", "relation": "imports", "confidence": "EXTRACTED", "source_file": "src\\main\\java\\kz\\hrms\\splitupauth\\entity\\AdminActionLog.java", "source_location": "L13", "weight": 1.0}, {"source": "adminactionlog", "target": "adminactionlog_adminactionlog", "relation": "contains", "confidence": "EXTRACTED", "source_file": "src\\main\\java\\kz\\hrms\\splitupauth\\entity\\AdminActionLog.java", "source_location": "L15", "weight": 1.0}, {"source": "adminactionlog_adminactionlog", "target": "adminactionlog_adminactionlog_oncreate", "relation": "method", "confidence": "EXTRACTED", "source_file": "src\\main\\java\\kz\\hrms\\splitupauth\\entity\\AdminActionLog.java", "source_location": "L70", "weight": 1.0}]}